LICENSE
MANIFEST.in
README.md
setup.py
tap_snapchat_ads/__init__.py
tap_snapchat_ads/client.py
tap_snapchat_ads/discover.py
tap_snapchat_ads/schema.py
tap_snapchat_ads/streams.py
tap_snapchat_ads/sync.py
tap_snapchat_ads.egg-info/PKG-INFO
tap_snapchat_ads.egg-info/SOURCES.txt
tap_snapchat_ads.egg-info/dependency_links.txt
tap_snapchat_ads.egg-info/entry_points.txt
tap_snapchat_ads.egg-info/requires.txt
tap_snapchat_ads.egg-info/top_level.txt
tap_snapchat_ads/schemas/ad_accounts.json
tap_snapchat_ads/schemas/ad_squads.json
tap_snapchat_ads/schemas/ads.json
tap_snapchat_ads/schemas/audience_segments.json
tap_snapchat_ads/schemas/billing_centers.json
tap_snapchat_ads/schemas/campaigns.json
tap_snapchat_ads/schemas/creatives.json
tap_snapchat_ads/schemas/funding_sources.json
tap_snapchat_ads/schemas/media.json
tap_snapchat_ads/schemas/members.json
tap_snapchat_ads/schemas/organizations.json
tap_snapchat_ads/schemas/phone_numbers.json
tap_snapchat_ads/schemas/pixel_domain_stats.json
tap_snapchat_ads/schemas/pixels.json
tap_snapchat_ads/schemas/product_catalogs.json
tap_snapchat_ads/schemas/product_sets.json
tap_snapchat_ads/schemas/roles.json
tap_snapchat_ads/schemas/shared/ad_account_stats.json
tap_snapchat_ads/schemas/shared/stats.json
tap_snapchat_ads/schemas/shared/targeting.json
tap_snapchat_ads/schemas/shared/targeting_geo.json
tests/test_all_fields.py
tests/test_automatic_fields.py
tests/test_bookmarks.py
tests/test_discovery.py
tests/test_interrupted_sync.py
tests/test_pagination.py
tests/test_parent_child_independent.py
tests/test_start_date.py