Metadata-Version: 2.1
Name: tap-snapchat-ads
Version: 0.2.0
Summary: Singer.io tap for extracting data from the Google Search Console API
Home-page: UNKNOWN
Author: jeff.huth@bytecode.io
License: UNKNOWN
Platform: UNKNOWN
Classifier: Programming Language :: Python :: 3 :: Only
Provides-Extra: dev
License-File: LICENSE
